geion/__init__.py
geion/genetic/__init__.py
geion/genetic/genome.py
geion/genetic/individual.py
geion/genetic/optimizer.py
geion/multicore/__init__.py
geion/multicore/backend.py
geion-1.0.0.dist-info/LICENSE
geion-1.0.0.dist-info/METADATA
geion-1.0.0.dist-info/WHEEL
geion-1.0.0.dist-info/top_level.txt
geion-1.0.0.dist-info/RECORD
