Metadata-Version: 2.1
Name: geion
Version: 1.0.0
Summary: Genetic Feature Optimization
Home-page: UNKNOWN
Author: Lleyton Ariton
Author-email: lleyton.ariton@gmail.com
License: UNKNOWN
Platform: UNKNOWN
Classifier: Programming Language :: Python :: 3
Classifier: License :: OSI Approved :: MIT License
Classifier: Operating System :: OS Independent
Requires-Python: >=3.6
